adjustable_random/__init__.py
adjustable_random/exceptions.py
adjustable_random/main.py
adjustable_random/tests.py
adjustable_random_package-1.1.dist-info/LICENSE
adjustable_random_package-1.1.dist-info/METADATA
adjustable_random_package-1.1.dist-info/WHEEL
adjustable_random_package-1.1.dist-info/top_level.txt
adjustable_random_package-1.1.dist-info/RECORD
