Metadata-Version: 2.1
Name: adjustable-random-package
Version: 1.1
Summary: Adjustable random number generator
Home-page: https://github.com/dinosaurtirex/adjustable-random
Author: dinosaurtirex
Author-email: sneakybeaky18@gmail.com
License: MIT
Requires-Python: >=3.10
License-File: LICENSE
Requires-Dist: matplotlib
